quaerere_base_client/__init__.py
quaerere_base_client/api.py
quaerere_base_client/client.py
quaerere_base_client/exceptions.py
quaerere_base_client/model.py
quaerere_base_client/resource.py
quaerere_base_client-0.1.0rc5.dist-info/LICENSE.txt
quaerere_base_client-0.1.0rc5.dist-info/METADATA
quaerere_base_client-0.1.0rc5.dist-info/WHEEL
quaerere_base_client-0.1.0rc5.dist-info/entry_points.txt
quaerere_base_client-0.1.0rc5.dist-info/top_level.txt
quaerere_base_client-0.1.0rc5.dist-info/RECORD
